atelParser/__init__.py
atelParser/__version__.py
atelParser/cl_utils.py
atelParser/default_settings.yaml
atelParser/download.py
atelParser/mysql.py
atelParser/test_settings.yaml
atelParser/utKit.py
atelParser/commonutils/__init__.py
atelParser/commonutils/getpackagepath.py
atelParser/tests/__init__.py
atelParser/tests/test_cl_utils.py
atelParser/tests/test_download.py
atelParser/tests/test_mysql.py
atelParser-1.0.2.dist-info/LICENSE
atelParser-1.0.2.dist-info/METADATA
atelParser-1.0.2.dist-info/WHEEL
atelParser-1.0.2.dist-info/entry_points.txt
atelParser-1.0.2.dist-info/top_level.txt
atelParser-1.0.2.dist-info/RECORD
