Metadata-Version: 2.1
Name: atelParser
Version: 1.0.2
Summary: scrape and parse content of ATels posted on The Astronomer's Telegram website, identify individual objects by name and coordinates
Home-page: https://github.com/thespacedoctor/atelParser
Download-URL: https://github.com/thespacedoctor/atelParser/archive/v1.0.2.zip
Author: David Young
Author-email: davidrobertyoung@gmail.com
License: MIT
Keywords: astronomy, parse, atel
Platform: UNKNOWN
Classifier: Development Status :: 4 - Beta
Classifier: License :: OSI Approved :: MIT License
Classifier: Programming Language :: Python :: 3.7
Classifier: Topic :: Utilities
License-File: LICENSE
Requires-Dist: pyyaml
Requires-Dist: atelParser
Requires-Dist: fundamentals
Requires-Dist: astrocalc
Requires-Dist: HMpTy
Requires-Dist: multiprocess
Requires-Dist: requests
Requires-Dist: pymysql
Requires-Dist: pandas
Requires-Dist: numpy
